onyx_extension/__init__.py
onyx_extension/_version.py
onyx_extension/handlers.py
onyx_extension-0.5.1.data/data/etc/jupyter/jupyter_server_config.d/onyx_extension.json
onyx_extension-0.5.1.data/data/share/jupyter/labextensions/onyx_extension/build_log.json
onyx_extension-0.5.1.data/data/share/jupyter/labextensions/onyx_extension/package.json
onyx_extension-0.5.1.data/data/share/jupyter/labextensions/onyx_extension/static/lib_index_js.3a74f3c1d376860d9381.js
onyx_extension-0.5.1.data/data/share/jupyter/labextensions/onyx_extension/static/lib_index_js.3a74f3c1d376860d9381.js.map
onyx_extension-0.5.1.data/data/share/jupyter/labextensions/onyx_extension/static/remoteEntry.663d5f3e7ecc1d28115a.js
onyx_extension-0.5.1.data/data/share/jupyter/labextensions/onyx_extension/static/remoteEntry.663d5f3e7ecc1d28115a.js.map
onyx_extension-0.5.1.data/data/share/jupyter/labextensions/onyx_extension/static/style.js
onyx_extension-0.5.1.data/data/share/jupyter/labextensions/onyx_extension/static/style_index_js-data_image_svg_xml_3csvg_xmlns_27http_www_w3_org_2000_svg_27_viewBox_27-4_-4_8-92e3d9.e75f2339a66e30d97fc1.js
onyx_extension-0.5.1.data/data/share/jupyter/labextensions/onyx_extension/static/style_index_js-data_image_svg_xml_3csvg_xmlns_27http_www_w3_org_2000_svg_27_viewBox_27-4_-4_8-92e3d9.e75f2339a66e30d97fc1.js.map
onyx_extension-0.5.1.data/data/share/jupyter/labextensions/onyx_extension/static/vendors-node_modules_climb-onyx-ui_dist_climb-onyx-ui_js.791605b0d91b7a146f93.js
onyx_extension-0.5.1.data/data/share/jupyter/labextensions/onyx_extension/static/vendors-node_modules_climb-onyx-ui_dist_climb-onyx-ui_js.791605b0d91b7a146f93.js.map
onyx_extension-0.5.1.data/data/share/jupyter/labextensions/onyx_extension/static/vendors-node_modules_style-loader_dist_runtime_injectStylesIntoStyleTag_js-node_modules_style-9a1b2d.638ae60612c637b0a694.js
onyx_extension-0.5.1.dist-info/METADATA
onyx_extension-0.5.1.dist-info/WHEEL
onyx_extension-0.5.1.dist-info/RECORD
